LICENSE
README.md
setup.py
dj_utilitybox/__init__.py
dj_utilitybox/__main__.py
dj_utilitybox/app.py
dj_utilitybox/dropdown/__init__.py
dj_utilitybox/dropdown/dropdown.py
dj_utilitybox/filters/__init__.py
dj_utilitybox/filters/generator.py
dj_utilitybox/response/__init__.py
dj_utilitybox/response/bad.py
dj_utilitybox/response/base.py
dj_utilitybox/response/good.py
dj_utilitybox/urls/__init__.py
dj_utilitybox/urls/path.py
dj_utilitybox/views/__init__.py
dj_utilitybox/views/base.py
django_utilitybox.egg-info/PKG-INFO
django_utilitybox.egg-info/SOURCES.txt
django_utilitybox.egg-info/dependency_links.txt
django_utilitybox.egg-info/entry_points.txt
django_utilitybox.egg-info/requires.txt
django_utilitybox.egg-info/top_level.txt
test/test.py