Metadata-Version: 2.1
Name: django-utilitybox
Version: 0.1.3
Summary: ...
Home-page: https://github.com/Josecolin99/...
Author: Jose Angel Colin Najera
Author-email: josecolin99@gmail.com
License: MIT
Classifier: Development Status :: 3 - Alpha
Classifier: Intended Audience :: Developers
Classifier: Topic :: Software Development :: Build Tools
Classifier: License :: OSI Approved :: MIT License
Classifier: Programming Language :: Python :: 3
License-File: LICENSE
